sloth_ci/ext/shields_io.py
sloth_ci.ext.shields_io-1.0.5.dist-info/DESCRIPTION.rst
sloth_ci.ext.shields_io-1.0.5.dist-info/METADATA
sloth_ci.ext.shields_io-1.0.5.dist-info/RECORD
sloth_ci.ext.shields_io-1.0.5.dist-info/WHEEL
sloth_ci.ext.shields_io-1.0.5.dist-info/metadata.json
sloth_ci.ext.shields_io-1.0.5.dist-info/top_level.txt
