Metadata-Version: 2.0
Name: sloth-ci.ext.shields-io
Version: 1.0.5
Summary: Status build shields for Sloth CI powered by http://shields.io
Home-page: https://bitbucket.org/sloth-ci/sloth-ci-extensions
Author: Konstantin Molchanov
Author-email: moigagoo@live.com
License: MIT
Platform: UNKNOWN
Classifier: Development Status :: 5 - Production/Stable
Classifier: Programming Language :: Python
Classifier: Programming Language :: Python :: 3
Requires-Dist: sloth-ci (>=2.1.1)
